{
  "title": "노르웨이의 숲",
  "authors": [
    "무라카미 하루키"
  ],
  "publisher": "민음사",
  "publishedDate": "2019-05-27",
  "description": "하루키 월드의 빛나는 다이아몬드 무라카미 하루키를 만나기 위해 가장 먼저 읽어야 할 책! 페이지를 처음 펼치는 오늘의 젊음들에게, 그리고 오랜 기억 속에 책의 한 구절을 간직하고 있는 어제의 젊음들에게, 한결같은 울림으로 예민하고 섬세한 청춘의 감성을 전하며 영원한 필독서로 사랑받고 있는 무라카미 하루키의 대표작 『노르웨이의 숲』. 1960년대 말 고도성장기 일본을 배경으로, 개인과 사회 사이의 금방이라도 무너질 듯한 관계와 손을 뻗으면 잡을 수 있을 것처럼 생생한 청춘의 순간을 그려 낸 이 소설은 36개국 이상의 국가에서 번역 소개되는 등 세계적인 ‘하루키 붐’을 일으키며 무라카미 하루키의 문학적 성과를 널리 알린 현대 일본 문학의 대표작이다.",
  "pageCount": 687,
  "categories": [
    "Literary Collections"
  ],
  "language": "ko",
  "google_books_id": "gDmaDwAAQBAJ",
  "image_url": "http://books.google.com/books/content?id=gDmaDwAAQBAJ&printsec=frontcover&img=1&zoom=1&edge=curl&source=gbs_api"
}